armpit/__init__.py
armpit/armpit.py
armpit/cli.py
armpit/update.py
armpit-1.2.0.dist-info/METADATA
armpit-1.2.0.dist-info/WHEEL
armpit-1.2.0.dist-info/entry_points.txt
armpit-1.2.0.dist-info/top_level.txt
armpit-1.2.0.dist-info/RECORD
