Metadata-Version: 2.4
Name: armpit
Version: 1.2.0
Summary: Python incremental revision
